src/__init__.py
src/cli.py
src/config.py
src/script.py
src/services/__init__.py
src/services/commits.py
src/services/jira_client.py
src/services/tempo_client.py
tempo_commit-0.1.2.dist-info/WHEEL
tempo_commit-0.1.2.dist-info/entry_points.txt
tempo_commit-0.1.2.dist-info/METADATA
tempo_commit-0.1.2.dist-info/RECORD
