Metadata-Version: 2.1
Name: tempo-commit
Version: 0.1.2
Summary: A cli tool to add a worklog to Tempo on commit
Author: Dinmukhamet Igissinov
Author-email: igissinov.d@gmail.com
Requires-Python: >=3.9,<4.0
Classifier: Programming Language :: Python :: 3
Classifier: Programming Language :: Python :: 3.9
Classifier: Programming Language :: Python :: 3.10
Classifier: Programming Language :: Python :: 3.11
Requires-Dist: asyncclick (>=8.1.7.1,<9.0.0.0)
Requires-Dist: gitpython (>=3.1.41,<4.0.0)
Requires-Dist: jira[cli] (>=3.6.0,<4.0.0)
Requires-Dist: loguru (>=0.7.2,<0.8.0)
Requires-Dist: python-dotenv (==0.20.0)
